halring/__init__.py
halring/_unittest/666666.py
halring/_unittest/77777.py
halring/_unittest/__init__.py
halring/_unittest/cty.py
halring/_unittest/test_artifactory_lib_util.py
halring/_unittest/test_case_config_parser_util.py
halring/_unittest/test_jira.py
halring/_unittest/test_linux.py
halring/_unittest/test_logging_util.py
halring/_unittest/test_loguru_util.py
halring/_unittest/test_windows_os_util.py
halring/apollo/__init__.py
halring/apollo/halring_apollo_opr.py
halring/artifactory_lib/__init__.py
halring/artifactory_lib/halring_artifactory_lib.py
halring/caseconfig/__init__.py
halring/caseconfig/parser.py
halring/common/__init__.py
halring/common/halring_common.py
halring/common/halring_const_variable.py
halring/common/halring_datetime.py
halring/common/halring_string.py
halring/confluence/__init__.py
halring/confluence/halring_confluence.py
halring/crypto/__init__.py
halring/crypto/halring_crypt.py
halring/date_time/__init__.py
halring/date_time/halring_datetime.py
halring/db_aqcdb/__init__.py
halring/db_aqcdb/halring_db_aqcdb.py
halring/excel/__init__.py
halring/excel/halring_excel.py
halring/ftp/__init__.py
halring/ftp/halring_ftp.py
halring/git/__init__.py
halring/git/halring_git.py
halring/jenkins_lib/__init__.py
halring/jenkins_lib/halring_jenkins.py
halring/jira_lib/__init__.py
halring/jira_lib/halring_jira.py
halring/json_lib/__init__.py
halring/json_lib/halring_json.py
halring/linux/__init__.py
halring/linux/halring_linux.py
halring/log/__init__.py
halring/log/halring_logging.py
halring/log/halring_loguru.py
halring/log/logging_util.py
halring/log/loguru_util.py
halring/mysql/__init__.py
halring/mysql/mysql_util.py
halring/mysql_lib/__init__.py
halring/mysql_lib/halring_mysql.py
halring/plink/__init__.py
halring/plink/halring_plink.py
halring/rabbitmq_lib/__init__.py
halring/rabbitmq_lib/halring_rabbitmq.py
halring/rds/__init__.py
halring/rds/rds_api_util.py
halring/rds_lib/__init__.py
halring/rds_lib/rds_api_util.py
halring/redis_lib/__init__.py
HalRing_Lib-1.1.0.dist-info/LICENSE
HalRing_Lib-1.1.0.dist-info/METADATA
HalRing_Lib-1.1.0.dist-info/WHEEL
HalRing_Lib-1.1.0.dist-info/top_level.txt
HalRing_Lib-1.1.0.dist-info/RECORD
